mdbook/__init__.py
mdbook/__main__.py
mdbook/cli.py
mdbook/domain/__init__.py
mdbook/domain/book.py
mdbook/domain/chapter.py
mdbook/domain/structure.py
mdbook/infrastructure/__init__.py
mdbook/infrastructure/container.py
mdbook/mcp/__init__.py
mdbook/mcp/server.py
mdbook/repositories/__init__.py
mdbook/repositories/config_repository.py
mdbook/repositories/file_repository.py
mdbook/repositories/interfaces.py
mdbook/services/__init__.py
mdbook/services/book_service.py
mdbook/services/interfaces.py
mdbook/services/reader_service.py
mdbook/services/structure_service.py
mdbook/services/writer_service.py
md_book-3.1.1.dist-info/METADATA
md_book-3.1.1.dist-info/WHEEL
md_book-3.1.1.dist-info/entry_points.txt
md_book-3.1.1.dist-info/licenses/LICENSE
md_book-3.1.1.dist-info/RECORD
