Metadata-Version: 2.4
Name: md-book
Version: 3.1.1
Summary: MD Book Tools - A DI/SOA markdown book reader and writer with MCP server support
Project-URL: Homepage, https://github.com/bobmatnyc/md-book
Project-URL: Repository, https://github.com/bobmatnyc/md-book
Project-URL: Documentation, https://github.com/bobmatnyc/md-book#readme
Author-email: Bob Matsuoka <bob@matsuoka.dev>
License: MIT
License-File: LICENSE
Keywords: book,bookdown,gitbook,leanpub,markdown,mcp,mdbook,reader,terminal,writer
Classifier: Development Status :: 4 - Beta
Classifier: Environment :: Console
Classifier: Intended Audience :: End Users/Desktop
Classifier: License :: OSI Approved :: MIT License
Classifier: Operating System :: OS Independent
Classifier: Programming Language :: Python :: 3
Classifier: Programming Language :: Python :: 3.10
Classifier: Programming Language :: Python :: 3.11
Classifier: Programming Language :: Python :: 3.12
Classifier: Programming Language :: Python :: 3.13
Classifier: Topic :: Documentation
Classifier: Topic :: Text Processing :: Markup :: Markdown
Requires-Python: >=3.10
Requires-Dist: click>=8.0.0
Requires-Dist: markdown>=3.4.0
Requires-Dist: mcp>=1.0.0
Requires-Dist: pygments>=2.14.0
Requires-Dist: pymdown-extensions>=9.0.0
Requires-Dist: pyyaml>=6.0.0
Requires-Dist: rich>=13.0.0
Provides-Extra: dev
Requires-Dist: build>=1.0.0; extra == 'dev'
Requires-Dist: pytest>=7.0.0; extra == 'dev'
Requires-Dist: twine>=4.0.0; extra == 'dev'
Provides-Extra: toml
Requires-Dist: tomli>=2.0.0; (python_version < '3.11') and extra == 'toml'
